btcmd
