Metadata-Version: 2.1
Name: btcmd
Version: 1.2
Summary: Bookmark Terminal Commands - btcmd
Home-page: https://github.com/gbhgit/bookmarked-terminal-commands
Download-URL: https://github.com/gbhgit/bookmarked-terminal-commands/archive/refs/tags/v.1.2.tar.gz
Author: Gabriel Bandeira and Wellington Mendes
Author-email: wellmend0@gmail.com
License: MIT
Keywords: terminal,bookmark,commands
Classifier: Development Status :: 4 - Beta
Classifier: Intended Audience :: Developers
Classifier: Topic :: Software Development :: Build Tools
Classifier: License :: OSI Approved :: MIT License
Classifier: Programming Language :: Python :: 3
Classifier: Topic :: Utilities
Classifier: Natural Language :: English
License-File: LICENSE
